[
  {
    "Pinyin1": "nǐ jīntiān yǒu shénme jìhuà ma ？",
    "Chinese1": "你今天有什么计划吗？",
    "Translate1": "Do you have any plans for today?"
  },
  {
    "Pinyin1": "wǒ dǎsuàn qù gòuwùzhōngxīn mǎi xiē yīfú 。",
    "Chinese1": "我打算去购物中心买些衣服。",
    "Translate1": "I plan to go to the mall and buy some clothes."
  },
  {
    "Pinyin1": "nǐ jiāzhù zài nǎlǐ ？",
    "Chinese1": "你家住在哪里？",
    "Translate1": "Where do you live?"
  },
  {
    "Pinyin1": "wǒ jīntiān gōngzuò máng 。",
    "Chinese1": "我今天工作忙。",
    "Translate1": "I'm busy with work today."
  },
  {
    "Pinyin1": "nǐ xǐhuan shénme yùndòng ？",
    "Chinese1": "你喜欢什么运动？",
    "Translate1": "Do you have any favorite sports?"
  },
  {
    "Pinyin1": "wǒ zuì xǐhuan chī zhōngguó cài 。",
    "Chinese1": "我最喜欢吃中国菜。",
    "Translate1": "I love eating Chinese food the most."
  },
  {
    "Pinyin1": "jīntiāntiānqì zhēn hǎo 。",
    "Chinese1": "今天天气真好。",
    "Translate1": "The weather is really nice today."
  },
  {
    "Pinyin1": "nǐ xǐhuan kànshū háishi kàn diànyǐng ？",
    "Chinese1": "你喜欢看书还是看电影？",
    "Translate1": "Do you like to read books or watch movies?"
  },
  {
    "Pinyin1": "wǒ zhēndé hǎohǎo xiūxi le 。",
    "Chinese1": "我真得好好休息了。",
    "Translate1": "I really need to rest well."
  },
  {
    "Pinyin1": "wǒ zuìjìn hěn máng 。",
    "Chinese1": "我最近很忙。",
    "Translate1": "I've been busy lately."
  },
  {
    "Pinyin1": "nǐ xǐhuan chī zhōngcān ma ？",
    "Chinese1": "你喜欢吃中餐吗？",
    "Translate1": "Do you like Chinese food?"
  },
  {
    "Pinyin1": "zhè shì wǒ de diànhuàhàomǎ 。",
    "Chinese1": "这是我的电话号码。",
    "Translate1": "This is my phone number."
  },
  {
    "Pinyin1": "nǐ zuìjìn yǒuméiyǒu shàngwǎng ？",
    "Chinese1": "你最近有没有上网？",
    "Translate1": "Have you been online recently?"
  },
  {
    "Pinyin1": "nǐ de wèizhi zěnmeyàng ？",
    "Chinese1": "你的位置怎么样？",
    "Translate1": "How's your location?"
  },
  {
    "Pinyin1": "wǒ juéde nàgè hěn yǒuqù 。",
    "Chinese1": "我觉得那个很有趣。",
    "Translate1": "I find that very interesting."
  },
  {
    "Pinyin1": "nǐ xǐhuan tīng yīnyuè ma ？",
    "Chinese1": "你喜欢听音乐吗？",
    "Translate1": "Do you like listening to music?"
  },
  {
    "Pinyin1": "wǒ xiǎng zū yīliàngchē 。",
    "Chinese1": "我想租一辆车。",
    "Translate1": "I want to rent a car."
  },
  {
    "Pinyin1": "zhège shì shénme ？",
    "Chinese1": "这个是什么？",
    "Translate1": "What is this?"
  },
  {
    "Pinyin1": "wǒ bù tài lǐjiě 。",
    "Chinese1": "我不太理解。",
    "Translate1": "I don't quite understand."
  },
  {
    "Pinyin1": "nǐ zhīdào zěnme zuò zhège ma ？",
    "Chinese1": "你知道怎么做这个吗？",
    "Translate1": "Do you know how to do this?"
  },
  {
    "Pinyin1": "wǒ ài chī bīngqílín 。",
    "Chinese1": "我爱吃冰淇淋。",
    "Translate1": "I love ice cream."
  },
  {
    "Pinyin1": "nǐ xǐhuan shénme yùndòng ？",
    "Chinese1": "你喜欢什么运动？",
    "Translate1": "What sports do you like?"
  },
  {
    "Pinyin1": "wǒ de hànyǔ bùhǎo 。",
    "Chinese1": "我的汉语不好。",
    "Translate1": "My Chinese is not good."
  },
  {
    "Pinyin1": "nǐ xǐhuan kànshū ma ？",
    "Chinese1": "你喜欢看书吗？",
    "Translate1": "Do you like reading books?"
  },
  {
    "Pinyin1": "wǒ xiǎng xuéxí xué hànyǔ 。",
    "Chinese1": "我想学习学汉语。",
    "Translate1": "I want to learn Chinese."
  },
  {
    "Pinyin1": "zhège fángjiān tàirè le 。",
    "Chinese1": "这个房间太热了。",
    "Translate1": "This room is too hot."
  },
  {
    "Pinyin1": "nǐ xǐhuan pǎobù ma ？",
    "Chinese1": "你喜欢跑步吗？",
    "Translate1": "Do you like running?"
  },
  {
    "Pinyin1": "wǒ xǐhuan lǚyóu 。",
    "Chinese1": "我喜欢旅游。",
    "Translate1": "I like traveling."
  },
  {
    "Pinyin1": "nǐ de yǎnjīng hěnpiāoliàng 。",
    "Chinese1": "你的眼睛很漂亮。",
    "Translate1": "Your eyes are beautiful."
  },
  {
    "Pinyin1": "wǒ yǒu liǎngzhī māo 。",
    "Chinese1": "我有两只猫。",
    "Translate1": "I have two cats."
  },
  {
    "Pinyin1": "wǒmen yǒu shíjiān 。",
    "Chinese1": "我们有时间。",
    "Translate1": "We have time."
  },
  {
    "Pinyin1": "nǐ zhège zhōumò yǒuméiyǒu kōng ？",
    "Chinese1": "你这个周末有没有空？",
    "Translate1": "Are you free this weekend?"
  },
  {
    "Pinyin1": "wǒmen chīfàn bā ！",
    "Chinese1": "我们吃饭吧！",
    "Translate1": "Let's eat!"
  },
  {
    "Pinyin1": "nǐ zuìjìn zěnmeyàng ？",
    "Chinese1": "你最近怎么样？",
    "Translate1": "How have you been lately?"
  },
  {
    "Pinyin1": "wǒ bù hējiǔ 。",
    "Chinese1": "我不喝酒。",
    "Translate1": "I don't drink alcohol."
  },
  {
    "Pinyin1": "wǒ xǐhuan qù yīnyuèhuì 。",
    "Chinese1": "我喜欢去音乐会。",
    "Translate1": "I enjoy going to concerts."
  },
  {
    "Pinyin1": "nǐ de péngyou duō ma ？",
    "Chinese1": "你的朋友多吗？",
    "Translate1": "Do you have many friends?"
  },
  {
    "Pinyin1": "wǒ méiyǒu diànnǎo 。",
    "Chinese1": "我没有电脑。",
    "Translate1": "I don't have a computer."
  },
  {
    "Pinyin1": "wǒ kěyǐ wèn nǐ yīgè wèntí ma ？",
    "Chinese1": "我可以问你一个问题吗？",
    "Translate1": "Can I ask you a question?"
  },
  {
    "Pinyin1": "nǐ zuìjìn kàn le nǎbù diànyǐng ？",
    "Chinese1": "你最近看了哪部电影？",
    "Translate1": "What movie did you watch recently?"
  },
  {
    "Pinyin1": "nǐ duō dà le ？",
    "Chinese1": "你多大了？",
    "Translate1": "How old are you?"
  },
  {
    "Pinyin1": "nǐ xǐhuan kàn xiǎoshuō ma ？",
    "Chinese1": "你喜欢看小说吗？",
    "Translate1": "Do you like reading novels?"
  },
  {
    "Pinyin1": "wǒ hěn xǐhuan kàn tiānkōng 。",
    "Chinese1": "我很喜欢看天空。",
    "Translate1": "I really enjoy looking at the sky."
  },
  {
    "Pinyin1": "wǒ juéde nǐ de yǎnjīng hěn měi 。",
    "Chinese1": "我觉得你的眼睛很美。",
    "Translate1": "I think your eyes are beautiful."
  },
  {
    "Pinyin1": "nǐ de yuànwàng shì shénme ？",
    "Chinese1": "你的愿望是什么？",
    "Translate1": "What is your wish?"
  },
  {
    "Pinyin1": "wǒmen kěyǐ yīqǐ chīfàn 。",
    "Chinese1": "我们可以一起吃饭。",
    "Translate1": "We can have dinner together."
  },
  {
    "Pinyin1": "nǐ zuò le shénme mèng ？",
    "Chinese1": "你做了什么梦？",
    "Translate1": "What did you dream about?"
  },
  {
    "Pinyin1": "wǒmen yīqǐ qù lǚyóu bā 。",
    "Chinese1": "我们一起去旅游吧。",
    "Translate1": "Let's travel together."
  },
  {
    "Pinyin1": "wǒmen yǒu liǎnggè háizi 。",
    "Chinese1": "我们有两个孩子。",
    "Translate1": "We have two children."
  },
  {
    "Pinyin1": "nǐ shénme shíhou huíjiā ？",
    "Chinese1": "你什么时候回家？",
    "Translate1": "When will you come home?"
  },
  {
    "Pinyin1": "wǒ zhù zài xībānyá 。",
    "Chinese1": "我住在西班牙。",
    "Translate1": "I live in Spain."
  },
  {
    "Pinyin1": "nǐ shénme shíhou qù lǚyóu ？",
    "Chinese1": "你什么时候去旅游？",
    "Translate1": "When are you going on a trip?"
  },
  {
    "Pinyin1": "wǒ xǐhuan chī sùshí 。",
    "Chinese1": "我喜欢吃素食。",
    "Translate1": "I like vegetarian food."
  },
  {
    "Pinyin1": "nǐ de yīfú hěnpiāoliàng 。",
    "Chinese1": "你的衣服很漂亮。",
    "Translate1": "Your clothes are beautiful."
  },
  {
    "Pinyin1": "wǒ xiǎng chūqù lǚyóu 。",
    "Chinese1": "我想出去旅游。",
    "Translate1": "I want to travel."
  },
  {
    "Pinyin1": "nǐ shì gànshénme gōngzuò de ？",
    "Chinese1": "你是干什么工作的？",
    "Translate1": "What do you do for work?"
  },
  {
    "Pinyin1": "zuìjìn wǒ bùgǎn chī yuèbǐng 。",
    "Chinese1": "最近我不敢吃月饼。",
    "Translate1": "I haven't dared to eat mooncakes recently."
  },
  {
    "Pinyin1": "nǐmen zhège zhōumò yǒuméiyǒu kōng ？",
    "Chinese1": "你们这个周末有没有空？",
    "Translate1": "Are you guys free this weekend?"
  },
  {
    "Pinyin1": "wǒ juéde nǐ shuō de hěn duì 。",
    "Chinese1": "我觉得你说的很对。",
    "Translate1": "I think you're right."
  },
  {
    "Pinyin1": "nǐmen xǐhuan wǔshù ma ？",
    "Chinese1": "你们喜欢武术吗？",
    "Translate1": "Do you guys like martial arts?"
  },
  {
    "Pinyin1": "wǒ zuìjìn zuò le hěnduō liànxí 。",
    "Chinese1": "我最近做了很多练习。",
    "Translate1": "I've done a lot of practice lately."
  },
  {
    "Pinyin1": "wǒmen zhège xīngqī yǐjīng hěnmáng le 。",
    "Chinese1": "我们这个星期已经很忙了。",
    "Translate1": "We've been very busy this week."
  },
  {
    "Pinyin1": "nǐ xiǎng zuò shénme ？",
    "Chinese1": "你想做什么？",
    "Translate1": "What do you want to do?"
  },
  {
    "Pinyin1": "wǒ zuìjìn duō le hěnduō shū 。",
    "Chinese1": "我最近多了很多书。",
    "Translate1": "I've bought a lot of books recently."
  },
  {
    "Pinyin1": "wǒ xǐhuan zài hùwàiyùndòng 。",
    "Chinese1": "我喜欢在户外运动。",
    "Translate1": "I like outdoor sports."
  },
  {
    "Pinyin1": "nǐ de yuànwàng shì shénme ？",
    "Chinese1": "你的愿望是什么？",
    "Translate1": "What's your wish?"
  },
  {
    "Pinyin1": "wǒmen kěyǐ xiān chīwǎnfàn 。",
    "Chinese1": "我们可以先吃晚饭。",
    "Translate1": "We can eat dinner first."
  },
  {
    "Pinyin1": "nǐ shénme shíhou kāishǐ shàngbān ？",
    "Chinese1": "你什么时候开始上班？",
    "Translate1": "When do you start work?"
  },
  {
    "Pinyin1": "nǐmen zhège xīngqīyī yǒuméiyǒu kōng ？",
    "Chinese1": "你们这个星期一有没有空？",
    "Translate1": "Are you guys free this Monday?"
  },
  {
    "Pinyin1": "wǒ juéde zhège diànyǐng hěn hǎokàn 。",
    "Chinese1": "我觉得这个电影很好看。",
    "Translate1": "I think this movie is great."
  },
  {
    "Pinyin1": "nǐ xiǎng chī zhōngguó cài háishi xīcān ？",
    "Chinese1": "你想吃中国菜还是西餐？",
    "Translate1": "Do you want to eat Chinese food or Western food?"
  },
  {
    "Pinyin1": "wǒ xiǎng xiànzài qù táoyuán 。",
    "Chinese1": "我想现在去桃园。",
    "Translate1": "I want to go to Taoyuan now."
  },
  {
    "Pinyin1": "nǐ xiǎng gěi wǒ jièshào shéi ？",
    "Chinese1": "你想给我介绍谁？",
    "Translate1": "Who do you want to introduce to me?"
  },
  {
    "Pinyin1": "wǒ juéde zhè shì wǒ de xìngqù 。",
    "Chinese1": "我觉得这是我的兴趣。",
    "Translate1": "I think this is my interest."
  },
  {
    "Pinyin1": "wǒ zuìjìn bù tàigāoxīng 。",
    "Chinese1": "我最近不太高兴。",
    "Translate1": "I haven't been very happy lately."
  },
  {
    "Pinyin1": "wǒmen kěyǐ chī bīngqílín 。",
    "Chinese1": "我们可以吃冰淇淋。",
    "Translate1": "We can eat ice cream."
  },
  {
    "Pinyin1": "nǐmen zhège xīngqīsān yǒuméiyǒu shíjiān chīwǎnfàn ？",
    "Chinese1": "你们这个星期三有没有时间吃晚饭？",
    "Translate1": "Do you have time for dinner this Wednesday?"
  },
  {
    "Pinyin1": "wǒ juéde zhège dōngxi hěn hǎochī 。",
    "Chinese1": "我觉得这个东西很好吃。",
    "Translate1": "I think this thing is delicious."
  },
  {
    "Pinyin1": "nǐ zuìjìn zài zuò shénme ？",
    "Chinese1": "你最近在做什么？",
    "Translate1": "What have you been up to lately?"
  },
  {
    "Pinyin1": "nǐ bù xǐhuan hēkāfēi ma ？",
    "Chinese1": "你不喜欢喝咖啡吗？",
    "Translate1": "Don't you like drinking coffee?"
  },
  {
    "Pinyin1": "nǐ juéde zhège dìfāng hěn yǒuqù ma ？",
    "Chinese1": "你觉得这个地方很有趣吗？",
    "Translate1": "Do you find this place interesting?"
  },
  {
    "Pinyin1": "nǐ xiǎng chī shénme zhōngguó cài ？",
    "Chinese1": "你想吃什么中国菜？",
    "Translate1": "What Chinese dish would you like to eat?"
  },
  {
    "Pinyin1": "nǐ xiǎng chī shénme shuǐguǒ ？",
    "Chinese1": "你想吃什么水果？",
    "Translate1": "What fruit would you like to eat?"
  },
  {
    "Pinyin1": "nǐ xiǎng hē shénme ？",
    "Chinese1": "你想喝什么？",
    "Translate1": "What would you like to drink?"
  },
  {
    "Pinyin1": "wǒ xiǎng hēchá 。",
    "Chinese1": "我想喝茶。",
    "Translate1": "I want to drink tea."
  },
  {
    "Pinyin1": "nǐ zuò guò fēijī ma ？",
    "Chinese1": "你做过飞机吗？",
    "Translate1": "Have you ever taken a plane?"
  },
  {
    "Pinyin1": "nǐ xiǎng shénme shíhou qù ？",
    "Chinese1": "你想什么时候去？",
    "Translate1": "When do you want to go?"
  },
  {
    "Pinyin1": "wǒ xiǎng xiànzài qù 。",
    "Chinese1": "我想现在去。",
    "Translate1": "I want to go now."
  },
  {
    "Pinyin1": "nǐ juéde zhège dōngxi hěn yǒuqù ma ？",
    "Chinese1": "你觉得这个东西很有趣吗？",
    "Translate1": "Do you find this thing interesting?"
  },
  {
    "Pinyin1": "nǐmen zhège xīngqī yǒuméiyǒu kōng ？",
    "Chinese1": "你们这个星期有没有空？",
    "Translate1": "Do you guys have any free time this week?"
  },
  {
    "Pinyin1": "wǒmen zhège xīngqī yǐjīng yǒu le jìhuà 。",
    "Chinese1": "我们这个星期已经有了计划。",
    "Translate1": "We already have plans for this week."
  },
  {
    "Pinyin1": "nǐ juéde zhège rén hěn yǒuqù ma ？",
    "Chinese1": "你觉得这个人很有趣吗？",
    "Translate1": "Do you find this person interesting?"
  },
  {
    "Pinyin1": "nǐ xiǎng chī shénme ？",
    "Chinese1": "你想吃什么？",
    "Translate1": "What do you want to eat?"
  },
  {
    "Pinyin1": "wǒ xiǎng chīhuǒguō 。",
    "Chinese1": "我想吃火锅。",
    "Translate1": "I want to eat hot pot."
  },
  {
    "Pinyin1": "nǐ xiǎng gěi wǒ jièshào shéi ？",
    "Chinese1": "你想给我介绍谁？",
    "Translate1": "Who would you like to introduce to me?"
  },
  {
    "Pinyin1": "nǐ xiǎng tīng shénme yīnyuè ？",
    "Chinese1": "你想听什么音乐？",
    "Translate1": "What music do you want to listen to?"
  },
  {
    "Pinyin1": "wǒ xiǎng tīng lǚyóu de gē 。",
    "Chinese1": "我想听旅游的歌。",
    "Translate1": "I want to listen to travel songs."
  },
  {
    "Pinyin1": "wǒ juéde zhège dìfāng hěn yǒuqù 。",
    "Chinese1": "我觉得这个地方很有趣。",
    "Translate1": "I find this place very interesting."
  },
  {
    "Pinyin1": "nǐ zěnmeyàng le ？",
    "Chinese1": "你怎么样了？",
    "Translate1": "How are you?"
  },
  {
    "Pinyin1": "duōshǎo qián ？",
    "Chinese1": "多少钱？",
    "Translate1": "How much does it cost?"
  },
  {
    "Pinyin1": "nǐ néng bāng wǒ yīxià ma ？",
    "Chinese1": "你能帮我一下吗？",
    "Translate1": "Can you help me?"
  },
  {
    "Pinyin1": "zǎoshanghǎo 。",
    "Chinese1": "早上好。",
    "Translate1": "Good morning."
  },
  {
    "Pinyin1": "wǎnshàng hǎo 。",
    "Chinese1": "晚上好。",
    "Translate1": "Good evening."
  },
  {
    "Pinyin1": "nǐ jiào shénme míngzì ？",
    "Chinese1": "你叫什么名字？",
    "Translate1": "What's your name?"
  },
  {
    "Pinyin1": "wǒ bù zhīdào 。",
    "Chinese1": "我不知道。",
    "Translate1": "I don't know."
  },
  {
    "Pinyin1": "nǐ xǐhuan chī shénme ？",
    "Chinese1": "你喜欢吃什么？",
    "Translate1": "What do you like to eat?"
  },
  {
    "Pinyin1": "wǒ ài chī zhōngguó cài 。",
    "Chinese1": "我爱吃中国菜。",
    "Translate1": "I love Chinese food."
  },
  {
    "Pinyin1": "nǐ zài nǎlǐ gōngzuò ？",
    "Chinese1": "你在哪里工作？",
    "Translate1": "Where do you work?"
  },
  {
    "Pinyin1": "wǒ zhù zài běijīng 。",
    "Chinese1": "我住在北京。",
    "Translate1": "I live in Beijing."
  },
  {
    "Pinyin1": "nǐ shuō dé hěn hǎo 。",
    "Chinese1": "你说得很好。",
    "Translate1": "You speak very well."
  },
  {
    "Pinyin1": "nǐ xǐhuan yùndòng ma ？",
    "Chinese1": "你喜欢运动吗？",
    "Translate1": "Do you like sports?"
  },
  {
    "Pinyin1": "wǒ tīzúqiú 。",
    "Chinese1": "我踢足球。",
    "Translate1": "I play soccer."
  },
  {
    "Pinyin1": "nǐ zuìjìn yǒuméiyǒu kōng ？",
    "Chinese1": "你最近有没有空？",
    "Translate1": "Are you free lately?"
  },
  {
    "Pinyin1": "nǐ de diànhuàhàomǎ shì duōshǎo ？",
    "Chinese1": "你的电话号码是多少？",
    "Translate1": "What's your phone number?"
  },
  {
    "Pinyin1": "nǐhǎo 。",
    "Chinese1": "你好。",
    "Translate1": "Hello."
  },
  {
    "Pinyin1": "wǒ bù míngbai 。",
    "Chinese1": "我不明白。",
    "Translate1": "I don't understand."
  },
  {
    "Pinyin1": "wǒ xūyào bāngzhù 。",
    "Chinese1": "我需要帮助。",
    "Translate1": "I need help."
  },
  {
    "Pinyin1": "nǐ juéde zěnmeyàng ？",
    "Chinese1": "你觉得怎么样？",
    "Translate1": "What do you think?"
  },
  {
    "Pinyin1": "nǐ huì zuò shénme ？",
    "Chinese1": "你会做什么？",
    "Translate1": "What can you do?"
  },
  {
    "Pinyin1": "nǐmen shì péngyou ma ？",
    "Chinese1": "你们是朋友吗？",
    "Translate1": "Are you friends?"
  },
  {
    "Pinyin1": "wǒ xiǎngyào zhège 。",
    "Chinese1": "我想要这个。",
    "Translate1": "I want this."
  },
  {
    "Pinyin1": "bùyòng kèqi 。",
    "Chinese1": "不用客气。",
    "Translate1": "You're welcome."
  },
  {
    "Pinyin1": "wǒ méiyǒu língqián 。",
    "Chinese1": "我没有零钱。",
    "Translate1": "I don't have change."
  },
  {
    "Pinyin1": "wǒyào yībēi kāfēi 。",
    "Chinese1": "我要一杯咖啡。",
    "Translate1": "I'd like a cup of coffee."
  },
  {
    "Pinyin1": "wǒ bù zhīdào zěnme qù 。",
    "Chinese1": "我不知道怎么去。",
    "Translate1": "I don't know how to get there."
  },
  {
    "Pinyin1": "wǒ chībuxià le 。",
    "Chinese1": "我吃不下了。",
    "Translate1": "I can't eat anymore."
  },
  {
    "Pinyin1": "zhèshì shénme ？",
    "Chinese1": "这是什么？",
    "Translate1": "What is this?"
  },
  {
    "Pinyin1": "zhège duōshǎo qián ？",
    "Chinese1": "这个多少钱？",
    "Translate1": "How much is this?"
  },
  {
    "Pinyin1": "nǐ zěnmehuíshì ？",
    "Chinese1": "你怎么回事？",
    "Translate1": "What's wrong with you?"
  },
  {
    "Pinyin1": "wǒ xiǎng qù sànbù 。",
    "Chinese1": "我想去散步。",
    "Translate1": "I want to take a walk."
  },
  {
    "Pinyin1": "wǒyào dào ...",
    "Chinese1": "我要到...",
    "Translate1": "I want to go to..."
  },
  {
    "Pinyin1": "nǐ jiéhūn le ma ？",
    "Chinese1": "你结婚了吗？",
    "Translate1": "Are you married?"
  },
  {
    "Pinyin1": "wǒ xiǎng gòuwù 。",
    "Chinese1": "我想购物。",
    "Translate1": "I want to go shopping."
  },
  {
    "Pinyin1": "nǐ néng bāng wǒ ma ？",
    "Chinese1": "你能帮我吗？",
    "Translate1": "Can you help me?"
  },
  {
    "Pinyin1": "wǒ hěn gāoxìng jiàndào nǐ 。",
    "Chinese1": "我很高兴见到你。",
    "Translate1": "I'm glad to meet you."
  },
  {
    "Pinyin1": "wǒ xūyào gēng duō de shíjiān 。",
    "Chinese1": "我需要更多的时间。",
    "Translate1": "I need more time."
  },
  {
    "Pinyin1": "wǒ xǐhuan zhèjiàn yīfú 。",
    "Chinese1": "我喜欢这件衣服。",
    "Translate1": "I like this piece of clothing."
  },
  {
    "Pinyin1": "nǐ kěyǐ zàishuō yībiàn ma ？",
    "Chinese1": "你可以再说一遍吗？",
    "Translate1": "Can you say it again?"
  },
  {
    "Pinyin1": "wǒ méiyǒu tīngdǒng 。",
    "Chinese1": "我没有听懂。",
    "Translate1": "I didn't understand."
  },
  {
    "Pinyin1": "suíshí liánxì wǒ 。",
    "Chinese1": "随时联系我。",
    "Translate1": "Contact me anytime."
  },
  {
    "Pinyin1": "wǒ xiǎng mǎi zhège 。",
    "Chinese1": "我想买这个。",
    "Translate1": "I want to buy this."
  },
  {
    "Pinyin1": "wǒ zhǐ xiǎng kànkan 。",
    "Chinese1": "我只想看看。",
    "Translate1": "I just want to look around."
  },
  {
    "Pinyin1": "zhèshì shénme cài ？",
    "Chinese1": "这是什么菜？",
    "Translate1": "What is this dish?"
  },
  {
    "Pinyin1": "wǒ xiǎng chī zhège 。",
    "Chinese1": "我想吃这个。",
    "Translate1": "I want to eat this."
  },
  {
    "Pinyin1": "nǐmen jiāyǒu zhège mài ma ？",
    "Chinese1": "你们家有这个卖吗？",
    "Translate1": "Do you sell this here?"
  },
  {
    "Pinyin1": "wǒ zài zhèlǐ mǎi le yīxiē dōngxi 。",
    "Chinese1": "我在这里买了一些东西。",
    "Translate1": "I bought some things here."
  },
  {
    "Pinyin1": "nǐmen zhèlǐ máng ma ？",
    "Chinese1": "你们这里忙吗？",
    "Translate1": "Are you busy here?"
  },
  {
    "Pinyin1": "zhège hěn piányi 。",
    "Chinese1": "这个很便宜。",
    "Translate1": "This is very cheap."
  },
  {
    "Pinyin1": "wǒ bù xūyào shōujù 。",
    "Chinese1": "我不需要收据。",
    "Translate1": "I don't need a receipt."
  },
  {
    "Pinyin1": "nǐmen yǒu chéngshì kǎ ma ？",
    "Chinese1": "你们有城市卡吗？",
    "Translate1": "Do you have city cards?"
  },
  {
    "Pinyin1": "wǒ xiǎng huàn zhège 。",
    "Chinese1": "我想换这个。",
    "Translate1": "I want to exchange this."
  },
  {
    "Pinyin1": "nǐmen jiēshòu wēixìn zhīfù ma ？",
    "Chinese1": "你们接受微信支付吗？",
    "Translate1": "Do you accept WeChat Pay?"
  },
  {
    "Pinyin1": "zhèshì mǎiyīsòngyī ma ？",
    "Chinese1": "这是买一送一吗？",
    "Translate1": "Is this buy one, get one free?"
  },
  {
    "Pinyin1": "nǐ yào bǎ zhège bāo qǐlai ma ？",
    "Chinese1": "你要把这个包起来吗？",
    "Translate1": "Can you wrap this up?"
  },
  {
    "Pinyin1": "wǒ bùyào bāo 。",
    "Chinese1": "我不要包。",
    "Translate1": "I don't want a bag."
  },
  {
    "Pinyin1": "nǐmen yǒu zhékòu ma ？",
    "Chinese1": "你们有折扣吗？",
    "Translate1": "Do you have any discounts?"
  },
  {
    "Pinyin1": "zhèlǐ yǒu yàofáng ma ？",
    "Chinese1": "这里有药房吗？",
    "Translate1": "Is there a pharmacy here?"
  },
  {
    "Pinyin1": "wǒ kěyǐ tíng zhèlǐ ma ？",
    "Chinese1": "我可以停这里吗？",
    "Translate1": "Can I park here?"
  },
  {
    "Pinyin1": "wǒ zài zhèlǐ zuò xiāoshòu 。",
    "Chinese1": "我在这里做销售。",
    "Translate1": "I work in sales here."
  },
  {
    "Pinyin1": "nǐmen kěyǐ jiàngjià ma ？",
    "Chinese1": "你们可以降价吗？",
    "Translate1": "Can you lower the price?"
  },
  {
    "Pinyin1": "zhèxiē dōngxi duōshǎo qián yīgè ？",
    "Chinese1": "这些东西多少钱一个？",
    "Translate1": "How much is one of these things?"
  },
  {
    "Pinyin1": "wǒ bù xǐhuan zhège yánsè 。",
    "Chinese1": "我不喜欢这个颜色。",
    "Translate1": "I don't like this color."
  },
  {
    "Pinyin1": "wǒhuì huílai de 。",
    "Chinese1": "我会回来的。",
    "Translate1": "I'll come back."
  },
  {
    "Pinyin1": "zhège hěn zhòng 。",
    "Chinese1": "这个很重。",
    "Translate1": "This is very heavy."
  },
  {
    "Pinyin1": "zhèlǐ yǒu shénme dōngxi ？",
    "Chinese1": "这里有什么东西？",
    "Translate1": "What's here?"
  },
  {
    "Pinyin1": "wǒ xiǎng mǎi miàntiáo 。",
    "Chinese1": "我想买面条。",
    "Translate1": "I want to buy noodles."
  },
  {
    "Pinyin1": "zǒuzǒukànkàn 。",
    "Chinese1": "走走看看。",
    "Translate1": "Let's walk around."
  },
  {
    "Pinyin1": "wǒmen xūyào mǐfàn 。",
    "Chinese1": "我们需要米饭。",
    "Translate1": "We need rice."
  },
  {
    "Pinyin1": "zhèlǐ yǒu xīnxiān shuǐguǒ ma ？",
    "Chinese1": "这里有新鲜水果吗？",
    "Translate1": "Do you have fresh fruits here?"
  },
  {
    "Pinyin1": "wǒ xiǎng mǎidiǎn yángròu 。",
    "Chinese1": "我想买点羊肉。",
    "Translate1": "I want to buy some lamb."
  },
  {
    "Pinyin1": "nǐmen de chāoshì hěndà 。",
    "Chinese1": "你们的超市很大。",
    "Translate1": "Your supermarket is big."
  },
  {
    "Pinyin1": "wǒyào mǎi xīnxiān de shūcài 。",
    "Chinese1": "我要买新鲜的蔬菜。",
    "Translate1": "I want to buy fresh vegetables."
  },
  {
    "Pinyin1": "nǐmen yǒu niúnǎi ma ？",
    "Chinese1": "你们有牛奶吗？",
    "Translate1": "Do you have milk?"
  },
  {
    "Pinyin1": "wǒyào xiǎo bǐnggān 。",
    "Chinese1": "我要小饼干。",
    "Translate1": "I want small cookies."
  },
  {
    "Pinyin1": "wǒ zhǐ xiǎng kànkan 。",
    "Chinese1": "我只想看看。",
    "Translate1": "I just want to browse."
  },
  {
    "Pinyin1": "zhèshì nǎlǐ ？",
    "Chinese1": "这是哪里？",
    "Translate1": "Where is this?"
  },
  {
    "Pinyin1": "wǒmen xūyào yán 。",
    "Chinese1": "我们需要盐。",
    "Translate1": "We need salt."
  },
  {
    "Pinyin1": "zhèlǐ de chāoshì fēicháng zhěngqí 。",
    "Chinese1": "这里的超市非常整齐。",
    "Translate1": "The supermarket here is very organized."
  },
  {
    "Pinyin1": "wǒyào mǎi yīxiē dàpíng de píjiǔ 。",
    "Chinese1": "我要买一些大瓶的啤酒。",
    "Translate1": "I want to buy some large bottles of beer."
  },
  {
    "Pinyin1": "nǐ yào zhège háishi nàgè ？",
    "Chinese1": "你要这个还是那个？",
    "Translate1": "Do you want this one or that one?"
  },
  {
    "Pinyin1": "wǒyào mǎi yībāo shūcài 。",
    "Chinese1": "我要买一包蔬菜。",
    "Translate1": "I want to buy a bag of vegetables."
  },
  {
    "Pinyin1": "wǒmen xūyào shālā 。",
    "Chinese1": "我们需要沙拉。",
    "Translate1": "We need salad."
  },
  {
    "Pinyin1": "wǒ zhǐyào yīzhī bǐ 。",
    "Chinese1": "我只要一只笔。",
    "Translate1": "I just want one pen."
  },
  {
    "Pinyin1": "jīntiān fēng hěndà 。",
    "Chinese1": "今天风很大。",
    "Translate1": "It's very windy today."
  },
  {
    "Pinyin1": "wǒ hěn xǐhuan tīng yīngwéngē 。",
    "Chinese1": "我很喜欢听英文歌。",
    "Translate1": "I like listening to English songs very much."
  },
  {
    "Pinyin1": "wǒ zuìjìn yīzhí zài jiànshēn 。",
    "Chinese1": "我最近一直在健身。",
    "Translate1": "I've been working out recently."
  },
  {
    "Pinyin1": "nǐ yǒu yùndòng de xíguàn ma ？",
    "Chinese1": "你有运动的习惯吗？",
    "Translate1": "Do you have any exercise habit?"
  },
  {
    "Pinyin1": "wǒ bùtàinéng chī là de dōngxi 。",
    "Chinese1": "我不太能吃辣的东西。",
    "Translate1": "I can't eat spicy food very well."
  },
  {
    "Pinyin1": "zhège chéngshì de dōngtiān tàilěng le 。",
    "Chinese1": "这个城市的冬天太冷了。",
    "Translate1": "The winter in this city is too cold."
  },
  {
    "Pinyin1": "jīntiān yùnqi hái bùcuò ！",
    "Chinese1": "今天运气还不错！",
    "Translate1": "Very lucky today!"
  },
  {
    "Pinyin1": "wǒ kěyǐ hé nǐmen yīqǐ chīwǎnfàn ma ？",
    "Chinese1": "我可以和你们一起吃晚饭吗？",
    "Translate1": "Can I have dinner with you?"
  },
  {
    "Pinyin1": "nǐ měitiān shénme shíhou xiàbān ？",
    "Chinese1": "你每天什么时候下班？",
    "Translate1": "What time do you get off work every day?"
  },
  {
    "Pinyin1": "wǒ hěn xǐhuan chī zhège tiánpǐn 。",
    "Chinese1": "我很喜欢吃这个甜品。",
    "Translate1": "I love eating this dessert."
  },
  {
    "Pinyin1": "míngtiān huì xiàyǔ ， nǐ jìde dàisǎn 。",
    "Chinese1": "明天会下雨，你记得带伞。",
    "Translate1": "It will rain tomorrow, remember to bring an umbrella."
  },
  {
    "Pinyin1": "wǒ xiǎng mǎi yītái diànnǎo 。",
    "Chinese1": "我想买一台电脑。",
    "Translate1": "I want to buy a computer."
  },
  {
    "Pinyin1": "míngtiān wǒmen yīqǐ qù xuéxiào bā 。",
    "Chinese1": "明天我们一起去学校吧。",
    "Translate1": "Let's go to school together tomorrow."
  },
  {
    "Pinyin1": "nǐ měitiān shénme shíhou shuìjiào ？",
    "Chinese1": "你每天什么时候睡觉？",
    "Translate1": "What time do you go to bed every day?"
  },
  {
    "Pinyin1": "wǒ měitiān dōu huì kàn jǐge xiǎoshí de shǒujī 。 dōu",
    "Chinese1": "我每天都会看几个小时的手机。",
    "Translate1": "I look at my phone for hours every day."
  },
  {
    "Pinyin1": "nǐ xǐhuan zìjǐ zuòfàn ma ？",
    "Chinese1": "你喜欢自己做饭吗？",
    "Translate1": "Do you like to cook for yourself?"
  },
  {
    "Pinyin1": "wǒ xǐhuan wányóuxì 。",
    "Chinese1": "我喜欢玩游戏。",
    "Translate1": "I like playing games."
  },
  {
    "Pinyin1": "nǐ xǐhuan shénme yàngshì de yīfú ？",
    "Chinese1": "你喜欢什么样式的衣服？",
    "Translate1": "What kind of clothes do you like?"
  },
  {
    "Pinyin1": "míngtiān jiǔdiǎn wǒmen shāngchǎng ménkǒu jiàn 。",
    "Chinese1": "明天九点我们商场门口见。",
    "Translate1": "We'll meet in front of the mall at nine o'clock tomorrow."
  },
  {
    "Pinyin1": "xiàgèyuè wǒmen qù lǚyóu bā 。",
    "Chinese1": "下个月我们去旅游吧。",
    "Translate1": "Let's go traveling next month."
  },
  {
    "Pinyin1": "míngtiān yào shàngbān ， jīnwǎn dé zǎodiǎn shuìjiào 。",
    "Chinese1": "明天要上班，今晚得早点睡觉。",
    "Translate1": "I have to go to work tomorrow and have to go to bed early tonight."
  },
  {
    "Pinyin1": "zhècì kǎoshì nǐ kǎodé zěnmeyàng ？",
    "Chinese1": "这次考试你考得怎么样？",
    "Translate1": "How did you do on this exam?"
  },
  {
    "Pinyin1": "wǒmen míngtiān jùcān ， nǐ yě lái bā 。",
    "Chinese1": "我们明天聚餐，你也来吧。",
    "Translate1": "We'll have dinner tomorrow, and you can come too."
  }
]